rfacts/__init__.py
rfacts-0.1.0.dist-info/LICENSE
rfacts-0.1.0.dist-info/METADATA
rfacts-0.1.0.dist-info/WHEEL
rfacts-0.1.0.dist-info/top_level.txt
rfacts-0.1.0.dist-info/RECORD
