Metadata-Version: 2.1
Name: rfacts
Version: 0.1.0
Summary: a very simple wrapper around requests/aiohttp for uselessfacts.jsph.pl
Home-page: https://github.com/anytarseir67/rfacts
Author: anytarseir67
Author-email: 
License: GPLv3
Platform: UNKNOWN
License-File: LICENSE
Requires-Dist: aiohttp
Requires-Dist: requests
